n1/ipam/__init__.py
n1/ipam/__main__.py
n1/ipam/_api.py
n1/ipam/_async/api.py
n1/ipam/_async/client.py
n1/ipam/_async/detect.py
n1/ipam/_async/scopes.py
n1/ipam/_client.py
n1/ipam/_config.py
n1/ipam/_scopes.py
n1/ipam/_settings.py
n1/ipam/_types.py
n1/ipam/cli/__init__.py
n1/ipam/cli/__main__.py
n1/ipam/cli/_envarg.py
n1/ipam/cli/opts.py
n1/ipam/consts.py
n1/ipam/detect.py
n1/ipam/extattr.py
n1/ipam/ipcalc.py
n1/ipam/models.py
n1/ipam/py.typed
n1/ipam/scopes_base.py
n1_ipam-0.2.2.dist-info/METADATA
n1_ipam-0.2.2.dist-info/WHEEL
n1_ipam-0.2.2.dist-info/entry_points.txt
n1_ipam-0.2.2.dist-info/RECORD
