Metadata-Version: 2.1
Name: n1-ipam
Version: 0.2.2
Summary: N1 IPAM
Author-Email: Kalle M. Aagaard <km@conscia.com>
License: MIT
Requires-Python: >=3.12
Requires-Dist: conscia-infoblox-sdk>=0.3.0
Requires-Dist: conscia-tasklog>=0.1.4
Requires-Dist: conscia-secretvalue>=0.1.196
Requires-Dist: tabulate>=0.9.0
Requires-Dist: pyyaml>=6.0.1
Requires-Dist: tabulate>=0.9.0; extra == "cli"
Requires-Dist: click>=8.1.7; extra == "cli"
Requires-Dist: click-option-group>=0.5.6; extra == "cli"
Requires-Dist: python-dotenv>=1.0.0; extra == "cli"
Provides-Extra: cli
